pytest_experiments/__init__.py
pytest_experiments/common.py
pytest_experiments/config.py
pytest_experiments/experiment.py
pytest_experiments/fixtures.py
pytest_experiments/json_tools.py
pytest_experiments/serde.py
pytest_experiments/store.py
pytest_experiments-0.1.1.dist-info/entry_points.txt
pytest_experiments-0.1.1.dist-info/LICENSE
pytest_experiments-0.1.1.dist-info/WHEEL
pytest_experiments-0.1.1.dist-info/METADATA
pytest_experiments-0.1.1.dist-info/RECORD
