Metadata-Version: 2.1
Name: pytest-experiments
Version: 0.1.1
Summary: A pytest plugin to help developers of research-oriented software projects keep track of the results of their numerical experiments.
Home-page: https://pytest-experiments.readthedocs.io/en/latest/
License: MIT
Author: Matt Battifarano
Author-email: matthew.battifarano@gmail.com
Requires-Python: >=3.7,<4.0
Classifier: Development Status :: 4 - Beta
Classifier: Framework :: Pytest
Classifier: Intended Audience :: Developers
Classifier: License :: OSI Approved :: MIT License
Classifier: Operating System :: OS Independent
Classifier: Programming Language :: Python
Classifier: Programming Language :: Python :: 3
Classifier: Programming Language :: Python :: 3 :: Only
Classifier: Programming Language :: Python :: 3.10
Classifier: Programming Language :: Python :: 3.7
Classifier: Programming Language :: Python :: 3.8
Classifier: Programming Language :: Python :: 3.9
Classifier: Programming Language :: Python :: Implementation :: CPython
Classifier: Topic :: Software Development :: Testing
Requires-Dist: SQLAlchemy (>=1.4.28,<2.0.0)
Requires-Dist: pytest (>=6.2.5,<7.0.0)
Project-URL: Repository, https://github.com/mbattifarano/pytest-experiments
